[{"linhvuc":"Bán Hàng","loaihinh":"PARTTIME","Namecompany":"Kazio","NameJob":"Research Associate","Address":"59445 Talmadge Road","ImageCompany":"job1.jpg","Detail":0.6982276855,"DetailCompany":1,"Phone":"379-425-2294","Email":"kmicheli0@nature.com","TimecreatPostDay":"10/23/2020","TimecreatPostHour":"5:29 PM"},
{"linhvuc":"Hành chính","loaihinh":"Thời vụ","Namecompany":"Agimba","NameJob":"Environmental Tech","Address":"1522 Victoria Point","ImageCompany":"job3.jpeg","Detail":0.1176095249,"DetailCompany":0,"Phone":"640-304-1210","Email":"mcroom1@gizmodo.com","TimecreatPostDay":"3/18/2020","TimecreatPostHour":"6:34 PM"},
{"linhvuc":"Hành chính","loaihinh":"Thực tập sinh","Namecompany":"Fiveclub","NameJob":"Director of Sales","Address":"56737 Green Trail","ImageCompany":"VLT.png","Detail":0.1887146654,"DetailCompany":0,"Phone":"746-877-6167","Email":"lskyrme2@sciencedaily.com","TimecreatPostDay":"2/9/2020","TimecreatPostHour":"1:13 AM"},
{"linhvuc":"Nhân sự","loaihinh":"Thực tập sinh","Namecompany":"Flipstorm","NameJob":"Desktop Support Technician","Address":"66 Victoria Pass","ImageCompany":"job2.png","Detail":0.2955421532,"DetailCompany":0,"Phone":"862-277-3193","Email":"jkalkofer3@wikia.com","TimecreatPostDay":"10/17/2020","TimecreatPostHour":"4:27 PM"},
{"linhvuc":"Tư vấn","loaihinh":"Thời vụ","Namecompany":"Eare","NameJob":"Recruiter","Address":"940 Jenifer Drive","ImageCompany":"job1.jpg","Detail":0.0614040126,"DetailCompany":1,"Phone":"482-259-7106","Email":"nklimshuk4@home.pl","TimecreatPostDay":"11/20/2020","TimecreatPostHour":"11:32 PM"},
{"linhvuc":"Nhà hàng","loaihinh":"PARTTIME","Namecompany":"Roodel","NameJob":"Media Manager I","Address":"262 Cordelia Trail","ImageCompany":"VLT.jpg","Detail":1.3683932656,"DetailCompany":1,"Phone":"117-110-8514","Email":"hkegan5@godaddy.com","TimecreatPostDay":"5/17/2020","TimecreatPostHour":"4:23 PM"},
{"linhvuc":"Tài chính","loaihinh":"Thời vụ","Namecompany":"Gigabox","NameJob":"Electrical Engineer","Address":"0 Mendota Avenue","ImageCompany":"job1.jpg","Detail":1.5704138773,"DetailCompany":1,"Phone":"804-366-4326","Email":"cpinnocke6@so-net.ne.jp","TimecreatPostDay":"2/12/2020","TimecreatPostHour":"2:34 PM"},
{"linhvuc":"Bảo hiểm","loaihinh":"PARTTIME","Namecompany":"Eazzy","NameJob":"Physical Therapy Assistant","Address":"0470 Orin Alley","ImageCompany":"job3.jpeg","Detail":0.4859733916,"DetailCompany":0,"Phone":"468-881-5763","Email":"tjoplin7@livejournal.com","TimecreatPostDay":"3/3/2020","TimecreatPostHour":"7:03 AM"},
{"linhvuc":"Du lịch","loaihinh":"PARTTIME","Namecompany":"Dabvine","NameJob":"Physical Therapy Assistant","Address":"50021 Ridgeview Crossing","ImageCompany":"job2.png","Detail":5.4546061892,"DetailCompany":1,"Phone":"219-886-4369","Email":"ccaldicot8@howstuffworks.com","TimecreatPostDay":"1/25/2020","TimecreatPostHour":"9:04 PM"},
{"linhvuc":"Kiểm toán","loaihinh":"Thực tập sinh","Namecompany":"Skippad","NameJob":"VP Product Management","Address":"2 Holmberg Avenue","ImageCompany":"job3.jpeg","Detail":0.0196395922,"DetailCompany":1,"Phone":"567-714-6090","Email":"hdolden9@furl.net","TimecreatPostDay":"9/2/2020","TimecreatPostHour":"3:49 PM"},
{"linhvuc":"Chăm sóc khách hàng","loaihinh":"Thực tập sinh","Namecompany":"Babbleblab","NameJob":"Executive Secretary","Address":"00 Forest Alley","ImageCompany":"job3.jpeg","Detail":1.9308013452,"DetailCompany":0,"Phone":"974-108-1094","Email":"ghazeldeana@devhub.com","TimecreatPostDay":"2/2/2020","TimecreatPostHour":"9:53 AM"},
{"linhvuc":"Kinh Doanh","loaihinh":"Thực tập sinh","Namecompany":"Photojam","NameJob":"Director of Sales","Address":"03 Dixon Trail","ImageCompany":"job1.jpg","Detail":1.8494493349,"DetailCompany":1,"Phone":"613-458-8009","Email":"pmullochb@newyorker.com","TimecreatPostDay":"9/13/2020","TimecreatPostHour":"9:13 PM"},
{"linhvuc":"Kế toán","loaihinh":"Thực tập sinh","Namecompany":"Pixope","NameJob":"Internal Auditor","Address":"16 Leroy Way","ImageCompany":"VLT.png","Detail":1.8495346986,"DetailCompany":0,"Phone":"243-738-5913","Email":"scumingc@timesonline.co.uk","TimecreatPostDay":"8/14/2020","TimecreatPostHour":"1:24 AM"},
{"linhvuc":"Model","loaihinh":"Thực tập sinh","Namecompany":"Abata","NameJob":"Accounting Assistant IV","Address":"8731 7th Center","ImageCompany":"job1.jpg","Detail":4.6605359302,"DetailCompany":0,"Phone":"526-197-0812","Email":"veayrsd@msu.edu","TimecreatPostDay":"9/27/2020","TimecreatPostHour":"12:01 PM"},
{"linhvuc":"Công nghệ thông tin","loaihinh":"FULLTIME","Namecompany":"Jaxbean","NameJob":"Community Outreach Specialist","Address":"8049 Arizona Hill","ImageCompany":"job2.png","Detail":0.2081762609,"DetailCompany":0,"Phone":"841-972-7786","Email":"gbeee@walmart.com","TimecreatPostDay":"11/11/2020","TimecreatPostHour":"12:34 PM"},
{"linhvuc":"Du lịch","loaihinh":"Thực tập sinh","Namecompany":"Leenti","NameJob":"Nurse","Address":"33877 Old Shore Terrace","ImageCompany":"job3.jpeg","Detail":1.4710277774,"DetailCompany":1,"Phone":"130-400-5066","Email":"mpowleyf@si.edu","TimecreatPostDay":"10/6/2020","TimecreatPostHour":"1:24 AM"},
{"linhvuc":"Nhân sự","loaihinh":"PARTTIME","Namecompany":"Buzzshare","NameJob":"GIS Technical Architect","Address":"4 Vera Avenue","ImageCompany":"VLT.jpg","Detail":0.940020897,"DetailCompany":1,"Phone":"793-491-2362","Email":"pgillimghamg@blogspot.com","TimecreatPostDay":"1/7/2020","TimecreatPostHour":"7:15 AM"},
{"linhvuc":"Kế toán","loaihinh":"Thời vụ","Namecompany":"Wordpedia","NameJob":"Structural Analysis Engineer","Address":"22 Jay Place","ImageCompany":"VLT.png","Detail":0.4594398487,"DetailCompany":1,"Phone":"299-412-5091","Email":"cpressnellh@simplemachines.org","TimecreatPostDay":"6/15/2020","TimecreatPostHour":"12:54 PM"},
{"linhvuc":"Du lịch","loaihinh":"FULLTIME","Namecompany":"Divanoodle","NameJob":"Nurse","Address":"374 Golf View Junction","ImageCompany":"job3.jpeg","Detail":0.8241131359,"DetailCompany":0,"Phone":"674-582-3472","Email":"kquineyi@bloglines.com","TimecreatPostDay":"10/22/2020","TimecreatPostHour":"6:15 AM"},
{"linhvuc":"Tài chính","loaihinh":"FULLTIME","Namecompany":"Demimbu","NameJob":"Quality Control Specialist","Address":"30 Anthes Plaza","ImageCompany":"VLT.png","Detail":1.8107607383,"DetailCompany":1,"Phone":"367-309-0975","Email":"pdasentj@privacy.gov.au","TimecreatPostDay":"2/2/2020","TimecreatPostHour":"9:51 PM"},
{"linhvuc":"Bảo hiểm","loaihinh":"FULLTIME","Namecompany":"Flashspan","NameJob":"Structural Analysis Engineer","Address":"8 American Road","ImageCompany":"VLT.jpg","Detail":0.4558052352,"DetailCompany":1,"Phone":"973-743-8784","Email":"aspearesk@umn.edu","TimecreatPostDay":"1/16/2020","TimecreatPostHour":"6:37 PM"},
{"linhvuc":"Model","loaihinh":"FULLTIME","Namecompany":"Jabbercube","NameJob":"VP Sales","Address":"8 Florence Drive","ImageCompany":"VLT.jpg","Detail":0.2128171668,"DetailCompany":1,"Phone":"938-117-9332","Email":"spheasantl@nationalgeographic.com","TimecreatPostDay":"10/30/2020","TimecreatPostHour":"1:46 PM"},
{"linhvuc":"Nhà hàng","loaihinh":"FULLTIME","Namecompany":"Wikizz","NameJob":"Geological Engineer","Address":"98 Anthes Terrace","ImageCompany":"VLT.png","Detail":1.6308377913,"DetailCompany":1,"Phone":"597-856-9382","Email":"fzavattierim@comsenz.com","TimecreatPostDay":"11/10/2020","TimecreatPostHour":"7:13 PM"},
{"linhvuc":"Bán Hàng","loaihinh":"Thực tập sinh","Namecompany":"Fatz","NameJob":"Software Engineer II","Address":"4120 Carioca Park","ImageCompany":"job2.png","Detail":1.3410947292,"DetailCompany":0,"Phone":"326-470-8658","Email":"sraspeln@yellowpages.com","TimecreatPostDay":"10/2/2020","TimecreatPostHour":"8:59 AM"},
{"linhvuc":"Nhân sự","loaihinh":"Thực tập sinh","Namecompany":"Zooxo","NameJob":"Statistician II","Address":"005 Summerview Pass","ImageCompany":"job2.png","Detail":0.5960435436,"DetailCompany":1,"Phone":"967-770-1389","Email":"pcaberaso@naver.com","TimecreatPostDay":"3/18/2020","TimecreatPostHour":"8:28 AM"},
{"linhvuc":"Kế toán","loaihinh":"FULLTIME","Namecompany":"Brainverse","NameJob":"Professor","Address":"870 Judy Pass","ImageCompany":"job3.jpeg","Detail":1.079659813,"DetailCompany":0,"Phone":"851-432-4637","Email":"emarciekp@dropbox.com","TimecreatPostDay":"7/25/2020","TimecreatPostHour":"1:23 AM"},
{"linhvuc":"Kiểm toán","loaihinh":"PARTTIME","Namecompany":"Dabtype","NameJob":"Community Outreach Specialist","Address":"20580 Corscot Lane","ImageCompany":"job3.jpeg","Detail":1.0049375975,"DetailCompany":0,"Phone":"558-446-0167","Email":"wronischq@sina.com.cn","TimecreatPostDay":"2/16/2020","TimecreatPostHour":"5:53 PM"},
{"linhvuc":"Ngân Hàng","loaihinh":"PARTTIME","Namecompany":"Cogibox","NameJob":"Business Systems Development Analyst","Address":"78 Knutson Circle","ImageCompany":"VLT.png","Detail":0.4257015068,"DetailCompany":1,"Phone":"558-149-7148","Email":"rhearlr@wisc.edu","TimecreatPostDay":"6/21/2020","TimecreatPostHour":"2:52 AM"},
{"linhvuc":"Bán Hàng","loaihinh":"Thời vụ","Namecompany":"Flashspan","NameJob":"Account Representative IV","Address":"5863 Bashford Trail","ImageCompany":"job1.jpg","Detail":0.9476869469,"DetailCompany":0,"Phone":"730-761-0447","Email":"jlupartos@berkeley.edu","TimecreatPostDay":"5/13/2020","TimecreatPostHour":"12:33 AM"},
{"linhvuc":"Bảo hiểm","loaihinh":"PARTTIME","Namecompany":"Thoughtworks","NameJob":"Environmental Specialist","Address":"2535 Union Alley","ImageCompany":"VLT.jpg","Detail":0.4105105593,"DetailCompany":0,"Phone":"363-102-8974","Email":"mbizleyt@tuttocitta.it","TimecreatPostDay":"2/25/2020","TimecreatPostHour":"9:55 AM"},
{"linhvuc":"Bảo hiểm","loaihinh":"PARTTIME","Namecompany":"Demimbu","NameJob":"VP Sales","Address":"709 Coleman Crossing","ImageCompany":"job1.jpg","Detail":1.0183299074,"DetailCompany":1,"Phone":"796-567-2993","Email":"brainsu@time.com","TimecreatPostDay":"1/21/2020","TimecreatPostHour":"9:19 AM"},
{"linhvuc":"Kiểm toán","loaihinh":"FULLTIME","Namecompany":"Linktype","NameJob":"Executive Secretary","Address":"533 Upham Center","ImageCompany":"job2.png","Detail":3.5159502527,"DetailCompany":0,"Phone":"596-746-3750","Email":"mcragoev@skype.com","TimecreatPostDay":"9/13/2020","TimecreatPostHour":"4:40 PM"},
{"linhvuc":"Parttime","loaihinh":"Thời vụ","Namecompany":"Skinte","NameJob":"Human Resources Manager","Address":"730 Caliangt Drive","ImageCompany":"VLT.jpg","Detail":0.1881490616,"DetailCompany":1,"Phone":"792-626-7336","Email":"kmiddasw@1688.com","TimecreatPostDay":"4/17/2020","TimecreatPostHour":"3:12 AM"},
{"linhvuc":"Nhà hàng","loaihinh":"Thực tập sinh","Namecompany":"Fivespan","NameJob":"Chief Design Engineer","Address":"010 Lien Avenue","ImageCompany":"job3.jpeg","Detail":0.0091928722,"DetailCompany":0,"Phone":"331-627-6723","Email":"eaidlerx@shop-pro.jp","TimecreatPostDay":"6/1/2020","TimecreatPostHour":"7:46 AM"},
{"linhvuc":"Giáo Dục","loaihinh":"Thời vụ","Namecompany":"Agimba","NameJob":"Payment Adjustment Coordinator","Address":"4776 Dunning Trail","ImageCompany":"job3.jpeg","Detail":1.1309634482,"DetailCompany":1,"Phone":"326-369-0523","Email":"ggostally@ca.gov","TimecreatPostDay":"1/8/2020","TimecreatPostHour":"11:27 PM"},
{"linhvuc":"Kế toán","loaihinh":"Thực tập sinh","Namecompany":"Realbuzz","NameJob":"Actuary","Address":"117 Cherokee Parkway","ImageCompany":"job3.jpeg","Detail":0.134387069,"DetailCompany":1,"Phone":"185-222-1055","Email":"tlockneyz@epa.gov","TimecreatPostDay":"1/9/2020","TimecreatPostHour":"5:43 PM"},
{"linhvuc":"Chăm sóc khách hàng","loaihinh":"Thực tập sinh","Namecompany":"Talane","NameJob":"Junior Executive","Address":"184 Lindbergh Hill","ImageCompany":"VLT.jpg","Detail":0.9176854335,"DetailCompany":0,"Phone":"371-840-6294","Email":"dsuddell10@cisco.com","TimecreatPostDay":"7/18/2020","TimecreatPostHour":"5:28 AM"},
{"linhvuc":"Giáo Dục","loaihinh":"FULLTIME","Namecompany":"Blogspan","NameJob":"Technical Writer","Address":"984 Pankratz Plaza","ImageCompany":"job1.jpg","Detail":1.3541362458,"DetailCompany":1,"Phone":"581-264-8326","Email":"apeyton11@vkontakte.ru","TimecreatPostDay":"1/29/2020","TimecreatPostHour":"7:41 AM"},
{"linhvuc":"Nhân sự","loaihinh":"FULLTIME","Namecompany":"Wikivu","NameJob":"Structural Analysis Engineer","Address":"8 Bobwhite Lane","ImageCompany":"VLT.jpg","Detail":0.7130460518,"DetailCompany":1,"Phone":"198-853-8801","Email":"yiorio12@oakley.com","TimecreatPostDay":"6/2/2020","TimecreatPostHour":"12:55 AM"},
{"linhvuc":"Tài chính","loaihinh":"Thực tập sinh","Namecompany":"Tagfeed","NameJob":"Senior Quality Engineer","Address":"40160 Lakeland Center","ImageCompany":"job2.png","Detail":0.3045666567,"DetailCompany":0,"Phone":"894-822-0982","Email":"lpods13@theglobeandmail.com","TimecreatPostDay":"3/26/2020","TimecreatPostHour":"2:16 AM"},
{"linhvuc":"Parttime","loaihinh":"FULLTIME","Namecompany":"Mita","NameJob":"Social Worker","Address":"4060 Warbler Avenue","ImageCompany":"job1.jpg","Detail":0.4378255545,"DetailCompany":0,"Phone":"359-219-3894","Email":"dparmenter14@jalbum.net","TimecreatPostDay":"9/13/2020","TimecreatPostHour":"6:59 AM"},
{"linhvuc":"Model","loaihinh":"FULLTIME","Namecompany":"Buzzdog","NameJob":"Quality Control Specialist","Address":"5 Buhler Junction","ImageCompany":"job2.png","Detail":0.556263455,"DetailCompany":0,"Phone":"383-556-6181","Email":"eanthon15@fc2.com","TimecreatPostDay":"12/31/2019","TimecreatPostHour":"8:27 PM"},
{"linhvuc":"Tư vấn","loaihinh":"FULLTIME","Namecompany":"Voonix","NameJob":"Internal Auditor","Address":"7 Rockefeller Trail","ImageCompany":"VLT.jpg","Detail":1.4486907468,"DetailCompany":1,"Phone":"240-119-0375","Email":"bplant16@engadget.com","TimecreatPostDay":"6/24/2020","TimecreatPostHour":"12:14 PM"},
{"linhvuc":"Giáo Dục","loaihinh":"PARTTIME","Namecompany":"BlogXS","NameJob":"Mechanical Systems Engineer","Address":"1495 Meadow Valley Pass","ImageCompany":"VLT.jpg","Detail":5.4549839059,"DetailCompany":1,"Phone":"241-640-6974","Email":"ljellico17@umich.edu","TimecreatPostDay":"2/9/2020","TimecreatPostHour":"4:19 AM"},
{"linhvuc":"Tư vấn","loaihinh":"PARTTIME","Namecompany":"JumpXS","NameJob":"Operator","Address":"5 Gina Trail","ImageCompany":"job2.png","Detail":0.1889392177,"DetailCompany":0,"Phone":"700-153-2659","Email":"rbarmadier18@usgs.gov","TimecreatPostDay":"3/5/2020","TimecreatPostHour":"3:16 PM"},
{"linhvuc":"Kế toán","loaihinh":"PARTTIME","Namecompany":"Flashdog","NameJob":"Nurse Practicioner","Address":"8 Hoard Pass","ImageCompany":"job3.jpeg","Detail":0.0273785352,"DetailCompany":0,"Phone":"447-108-0437","Email":"ttrippitt19@google.com","TimecreatPostDay":"9/7/2020","TimecreatPostHour":"6:18 AM"},
{"linhvuc":"Nhân sự","loaihinh":"PARTTIME","Namecompany":"Fivespan","NameJob":"Project Manager","Address":"4757 Heath Way","ImageCompany":"VLT.jpg","Detail":2.0530109368,"DetailCompany":0,"Phone":"203-399-3988","Email":"jmatisoff1a@digg.com","TimecreatPostDay":"5/25/2020","TimecreatPostHour":"4:44 PM"},
{"linhvuc":"Nhà hàng","loaihinh":"FULLTIME","Namecompany":"JumpXS","NameJob":"Account Representative I","Address":"158 Lyons Alley","ImageCompany":"VLT.jpg","Detail":1.1190916597,"DetailCompany":0,"Phone":"771-504-6751","Email":"cattenborough1b@walmart.com","TimecreatPostDay":"4/3/2020","TimecreatPostHour":"7:31 AM"},
{"linhvuc":"Bảo hiểm","loaihinh":"FULLTIME","Namecompany":"Avaveo","NameJob":"Analog Circuit Design manager","Address":"481 Petterle Place","ImageCompany":"job2.png","Detail":0.8994396785,"DetailCompany":1,"Phone":"672-505-4556","Email":"thenriquet1c@cbsnews.com","TimecreatPostDay":"4/21/2020","TimecreatPostHour":"9:58 AM"},
{"linhvuc":"Tài chính","loaihinh":"FULLTIME","Namecompany":"Flipstorm","NameJob":"Media Manager I","Address":"007 Jenifer Pass","ImageCompany":"job1.jpg","Detail":0.5861836057,"DetailCompany":1,"Phone":"734-478-2692","Email":"ktrain1d@hubpages.com","TimecreatPostDay":"9/30/2020","TimecreatPostHour":"8:33 PM"},
{"linhvuc":"Tài chính","loaihinh":"PARTTIME","Namecompany":"Meedoo","NameJob":"Food Chemist","Address":"9 Londonderry Lane","ImageCompany":"job1.jpg","Detail":1.2395806569,"DetailCompany":1,"Phone":"819-338-8189","Email":"lpelerin1e@tiny.cc","TimecreatPostDay":"5/31/2020","TimecreatPostHour":"7:28 PM"},
{"linhvuc":"Chăm sóc khách hàng","loaihinh":"Thực tập sinh","Namecompany":"Yakitri","NameJob":"General Manager","Address":"41 Quincy Junction","ImageCompany":"VLT.jpg","Detail":1.1164270128,"DetailCompany":1,"Phone":"139-275-4746","Email":"rmewes1f@vkontakte.ru","TimecreatPostDay":"2/15/2020","TimecreatPostHour":"7:58 AM"},
{"linhvuc":"Công nghệ thông tin","loaihinh":"PARTTIME","Namecompany":"Livetube","NameJob":"Help Desk Operator","Address":"207 Transport Court","ImageCompany":"job1.jpg","Detail":2.9210472696,"DetailCompany":1,"Phone":"581-432-6608","Email":"cfishleigh1g@weebly.com","TimecreatPostDay":"2/9/2020","TimecreatPostHour":"4:38 PM"},
{"linhvuc":"Công nghệ thông tin","loaihinh":"PARTTIME","Namecompany":"Quimba","NameJob":"Engineer IV","Address":"70 Burning Wood Road","ImageCompany":"job3.jpeg","Detail":1.8874610043,"DetailCompany":1,"Phone":"175-468-1262","Email":"svolk1h@taobao.com","TimecreatPostDay":"6/16/2020","TimecreatPostHour":"2:47 PM"},
{"linhvuc":"Bán Hàng","loaihinh":"PARTTIME","Namecompany":"Meetz","NameJob":"Librarian","Address":"46049 Rieder Lane","ImageCompany":"VLT.png","Detail":1.1679297768,"DetailCompany":1,"Phone":"382-540-2926","Email":"jcapstick1i@gravatar.com","TimecreatPostDay":"11/3/2020","TimecreatPostHour":"9:48 PM"},
{"linhvuc":"Công nghệ thông tin","loaihinh":"PARTTIME","Namecompany":"Tavu","NameJob":"Software Engineer I","Address":"854 Waywood Way","ImageCompany":"job2.png","Detail":1.1969224314,"DetailCompany":0,"Phone":"101-223-1744","Email":"jpedrielli1j@naver.com","TimecreatPostDay":"2/15/2020","TimecreatPostHour":"5:05 AM"},
{"linhvuc":"Tư vấn","loaihinh":"FULLTIME","Namecompany":"Blogtag","NameJob":"Technical Writer","Address":"2 Debs Way","ImageCompany":"job2.png","Detail":0.2885468137,"DetailCompany":0,"Phone":"375-275-8712","Email":"lmayfield1k@microsoft.com","TimecreatPostDay":"6/28/2020","TimecreatPostHour":"10:04 AM"},
{"linhvuc":"Du lịch","loaihinh":"FULLTIME","Namecompany":"Dynazzy","NameJob":"Electrical Engineer","Address":"28377 American Ash Drive","ImageCompany":"job2.png","Detail":0.8118391312,"DetailCompany":1,"Phone":"720-784-1568","Email":"ereeder1l@twitpic.com","TimecreatPostDay":"4/10/2020","TimecreatPostHour":"4:41 PM"},
{"linhvuc":"Tư vấn","loaihinh":"Thời vụ","Namecompany":"Cogidoo","NameJob":"Senior Financial Analyst","Address":"52 Haas Avenue","ImageCompany":"VLT.png","Detail":1.4517830759,"DetailCompany":1,"Phone":"228-191-7287","Email":"ysabbin1m@e-recht24.de","TimecreatPostDay":"3/23/2020","TimecreatPostHour":"12:19 PM"},
{"linhvuc":"Tư vấn","loaihinh":"Thời vụ","Namecompany":"Mymm","NameJob":"Recruiter","Address":"8 4th Trail","ImageCompany":"job1.jpg","Detail":0.207531427,"DetailCompany":1,"Phone":"233-390-7565","Email":"srennocks1n@unblog.fr","TimecreatPostDay":"8/24/2020","TimecreatPostHour":"3:27 AM"},
{"linhvuc":"Chăm sóc khách hàng","loaihinh":"FULLTIME","Namecompany":"Zoovu","NameJob":"Cost Accountant","Address":"01 John Wall Point","ImageCompany":"job3.jpeg","Detail":0.4919452506,"DetailCompany":0,"Phone":"859-701-6887","Email":"dlathee1o@thetimes.co.uk","TimecreatPostDay":"12/30/2019","TimecreatPostHour":"8:12 AM"},
{"linhvuc":"Kiểm toán","loaihinh":"Thực tập sinh","Namecompany":"Fatz","NameJob":"Community Outreach Specialist","Address":"63 Cody Plaza","ImageCompany":"job2.png","Detail":1.8725565644,"DetailCompany":1,"Phone":"242-101-1921","Email":"hlamborn1p@alibaba.com","TimecreatPostDay":"1/10/2020","TimecreatPostHour":"8:12 PM"},
{"linhvuc":"Tư vấn","loaihinh":"PARTTIME","Namecompany":"Yabox","NameJob":"Media Manager I","Address":"4 Cottonwood Alley","ImageCompany":"job3.jpeg","Detail":1.9922918107,"DetailCompany":0,"Phone":"-881-7457","Email":"dsuckling1q@virginia.edu","TimecreatPostDay":"6/17/2020","TimecreatPostHour":"6:12 PM"},
{"linhvuc":"Kiểm toán","loaihinh":"PARTTIME","Namecompany":"Yoveo","NameJob":"Senior Editor","Address":"392 Forest Run Avenue","ImageCompany":"VLT.png","Detail":0.606408656,"DetailCompany":1,"Phone":"852-111-0885","Email":"svolker1r@twitter.com","TimecreatPostDay":"9/9/2020","TimecreatPostHour":"4:24 AM"},
{"linhvuc":"Kiểm toán","loaihinh":"FULLTIME","Namecompany":"Voonder","NameJob":"Senior Editor","Address":"40032 Calypso Park","ImageCompany":"job1.jpg","Detail":1.416837738,"DetailCompany":1,"Phone":"244-703-2871","Email":"lreignould1s@phpbb.com","TimecreatPostDay":"7/29/2020","TimecreatPostHour":"11:07 PM"},
{"linhvuc":"Giáo Dục","loaihinh":"PARTTIME","Namecompany":"Latz","NameJob":"Financial Analyst","Address":"9197 Lyons Center","ImageCompany":"VLT.jpg","Detail":0.5704121848,"DetailCompany":1,"Phone":"740-109-4130","Email":"druthven1t@un.org","TimecreatPostDay":"3/14/2020","TimecreatPostHour":"7:07 AM"},
{"linhvuc":"Ngân Hàng","loaihinh":"Thời vụ","Namecompany":"InnoZ","NameJob":"Structural Engineer","Address":"0751 Thierer Pass","ImageCompany":"job2.png","Detail":0.0000234121,"DetailCompany":0,"Phone":"212-336-0827","Email":"dcuvley1u@stumbleupon.com","TimecreatPostDay":"8/24/2020","TimecreatPostHour":"2:01 AM"},
{"linhvuc":"Hành chính","loaihinh":"FULLTIME","Namecompany":"Wordify","NameJob":"Community Outreach Specialist","Address":"8631 Oakridge Junction","ImageCompany":"job3.jpeg","Detail":1.10506366,"DetailCompany":1,"Phone":"589-627-1295","Email":"yollivier1v@samsung.com","TimecreatPostDay":"4/29/2020","TimecreatPostHour":"8:28 AM"},
{"linhvuc":"Công nghệ thông tin","loaihinh":"PARTTIME","Namecompany":"Fivespan","NameJob":"Librarian","Address":"239 Ryan Plaza","ImageCompany":"job2.png","Detail":0.2392184703,"DetailCompany":0,"Phone":"292-383-8011","Email":"sauld1w@examiner.com","TimecreatPostDay":"12/13/2019","TimecreatPostHour":"8:32 PM"},
{"linhvuc":"Hành chính","loaihinh":"Thời vụ","Namecompany":"Wikido","NameJob":"Cost Accountant","Address":"9468 Northfield Lane","ImageCompany":"VLT.png","Detail":1.3466631696,"DetailCompany":1,"Phone":"386-480-6166","Email":"cmattiazzi1x@sitemeter.com","TimecreatPostDay":"5/10/2020","TimecreatPostHour":"8:54 PM"},
{"linhvuc":"Ngân Hàng","loaihinh":"Thực tập sinh","Namecompany":"Livetube","NameJob":"Senior Sales Associate","Address":"57 Homewood Center","ImageCompany":"job1.jpg","Detail":0.8595624692,"DetailCompany":1,"Phone":"522-499-3419","Email":"ocosgrave1y@i2i.jp","TimecreatPostDay":"3/3/2020","TimecreatPostHour":"1:30 AM"},
{"linhvuc":"Giáo Dục","loaihinh":"Thời vụ","Namecompany":"Trudoo","NameJob":"Geological Engineer","Address":"49 Arkansas Court","ImageCompany":"VLT.jpg","Detail":0.5066456005,"DetailCompany":1,"Phone":"719-520-0975","Email":"cbaggaley1z@examiner.com","TimecreatPostDay":"11/17/2020","TimecreatPostHour":"8:36 PM"},
{"linhvuc":"Hành chính","loaihinh":"PARTTIME","Namecompany":"Roombo","NameJob":"Quality Control Specialist","Address":"540 American Ash Trail","ImageCompany":"job2.png","Detail":0.3106433808,"DetailCompany":1,"Phone":"502-443-0909","Email":"gruecastle20@e-recht24.de","TimecreatPostDay":"8/27/2020","TimecreatPostHour":"7:29 PM"},
{"linhvuc":"Nhân sự","loaihinh":"PARTTIME","Namecompany":"Mybuzz","NameJob":"Account Coordinator","Address":"01463 Lerdahl Lane","ImageCompany":"job2.png","Detail":1.1689459991,"DetailCompany":1,"Phone":"478-347-0027","Email":"acutteridge21@jalbum.net","TimecreatPostDay":"1/6/2020","TimecreatPostHour":"10:33 PM"},
{"linhvuc":"Nhà hàng","loaihinh":"Thực tập sinh","Namecompany":"Yozio","NameJob":"Business Systems Development Analyst","Address":"1 Dryden Center","ImageCompany":"job2.png","Detail":1.1455048989,"DetailCompany":0,"Phone":"493-767-4216","Email":"tmorriss22@census.gov","TimecreatPostDay":"8/12/2020","TimecreatPostHour":"5:03 AM"},
{"linhvuc":"Hành chính","loaihinh":"FULLTIME","Namecompany":"Edgeclub","NameJob":"Project Manager","Address":"5 Hauk Point","ImageCompany":"VLT.png","Detail":2.4529986753,"DetailCompany":1,"Phone":"271-599-4178","Email":"achallenor23@sina.com.cn","TimecreatPostDay":"10/1/2020","TimecreatPostHour":"12:05 PM"},
{"linhvuc":"Tư vấn","loaihinh":"Thực tập sinh","Namecompany":"Gigaclub","NameJob":"Programmer II","Address":"94713 Fordem Crossing","ImageCompany":"job3.jpeg","Detail":0.1153513064,"DetailCompany":1,"Phone":"317-286-1801","Email":"qfraney24@tripod.com","TimecreatPostDay":"7/2/2020","TimecreatPostHour":"1:13 AM"},
{"linhvuc":"Hành chính","loaihinh":"FULLTIME","Namecompany":"Eabox","NameJob":"Recruiting Manager","Address":"742 Sycamore Hill","ImageCompany":"job2.png","Detail":0.3208552905,"DetailCompany":1,"Phone":"149-150-6294","Email":"sstayte25@si.edu","TimecreatPostDay":"10/17/2020","TimecreatPostHour":"1:20 AM"},
{"linhvuc":"Kế toán","loaihinh":"Thời vụ","Namecompany":"Skivee","NameJob":"Recruiting Manager","Address":"2787 Mockingbird Point","ImageCompany":"VLT.jpg","Detail":0.1282992884,"DetailCompany":1,"Phone":"554-947-1308","Email":"hgillingham26@abc.net.au","TimecreatPostDay":"2/24/2020","TimecreatPostHour":"12:01 PM"},
{"linhvuc":"Nhân sự","loaihinh":"PARTTIME","Namecompany":"Youspan","NameJob":"Programmer I","Address":"5 Ridge Oak Court","ImageCompany":"VLT.png","Detail":4.9749962275,"DetailCompany":1,"Phone":"928-689-7861","Email":"aclementson27@miibeian.gov.cn","TimecreatPostDay":"7/30/2020","TimecreatPostHour":"5:13 PM"},
{"linhvuc":"Nhà hàng","loaihinh":"PARTTIME","Namecompany":"Yodo","NameJob":"Technical Writer","Address":"4641 Rusk Point","ImageCompany":"VLT.png","Detail":1.8805346184,"DetailCompany":1,"Phone":"359-477-9065","Email":"bnardoni28@spotify.com","TimecreatPostDay":"2/22/2020","TimecreatPostHour":"3:03 PM"},
{"linhvuc":"Hành chính","loaihinh":"Thời vụ","Namecompany":"Skinix","NameJob":"Quality Control Specialist","Address":"5 Warner Center","ImageCompany":"job3.jpeg","Detail":0.6016803556,"DetailCompany":1,"Phone":"382-921-0359","Email":"fridgewell29@umich.edu","TimecreatPostDay":"1/25/2020","TimecreatPostHour":"5:24 AM"},
{"linhvuc":"Du lịch","loaihinh":"FULLTIME","Namecompany":"Kwinu","NameJob":"Physical Therapy Assistant","Address":"3 8th Avenue","ImageCompany":"VLT.jpg","Detail":0.5217927642,"DetailCompany":1,"Phone":"195-818-8819","Email":"rantonognoli2a@homestead.com","TimecreatPostDay":"2/18/2020","TimecreatPostHour":"7:40 PM"},
{"linhvuc":"Parttime","loaihinh":"FULLTIME","Namecompany":"Dynava","NameJob":"Accountant IV","Address":"7 Artisan Place","ImageCompany":"job2.png","Detail":0.3840629086,"DetailCompany":0,"Phone":"797-407-8528","Email":"kivashinnikov2b@sohu.com","TimecreatPostDay":"2/25/2020","TimecreatPostHour":"7:08 PM"},
{"linhvuc":"Tài chính","loaihinh":"PARTTIME","Namecompany":"Vitz","NameJob":"Cost Accountant","Address":"5150 Bunting Plaza","ImageCompany":"job2.png","Detail":0.0513555121,"DetailCompany":1,"Phone":"150-385-7553","Email":"ccoleford2c@youtube.com","TimecreatPostDay":"11/15/2020","TimecreatPostHour":"2:55 AM"},
{"linhvuc":"Nhân sự","loaihinh":"Thời vụ","Namecompany":"Fiveclub","NameJob":"Senior Sales Associate","Address":"2930 Cascade Park","ImageCompany":"job1.jpg","Detail":1.2948181371,"DetailCompany":1,"Phone":"696-423-1198","Email":"jcortese2d@booking.com","TimecreatPostDay":"3/31/2020","TimecreatPostHour":"4:30 AM"},
{"linhvuc":"Du lịch","loaihinh":"PARTTIME","Namecompany":"Jabberbean","NameJob":"Registered Nurse","Address":"4 Thackeray Plaza","ImageCompany":"job2.png","Detail":0.6256740212,"DetailCompany":0,"Phone":"451-162-4541","Email":"areams2e@dmoz.org","TimecreatPostDay":"1/14/2020","TimecreatPostHour":"1:45 AM"},
{"linhvuc":"Nhân sự","loaihinh":"FULLTIME","Namecompany":"Lajo","NameJob":"Senior Editor","Address":"024 Bashford Point","ImageCompany":"job3.jpeg","Detail":2.1743945888,"DetailCompany":0,"Phone":"846-596-2590","Email":"mhenriet2f@auda.org.au","TimecreatPostDay":"1/28/2020","TimecreatPostHour":"2:54 AM"},
{"linhvuc":"Nhà hàng","loaihinh":"Thực tập sinh","Namecompany":"Mymm","NameJob":"Quality Engineer","Address":"167 Dexter Way","ImageCompany":"VLT.jpg","Detail":2.5247301674,"DetailCompany":1,"Phone":"349-399-4439","Email":"bdobbson2g@jimdo.com","TimecreatPostDay":"11/8/2020","TimecreatPostHour":"9:58 PM"},
{"linhvuc":"Parttime","loaihinh":"FULLTIME","Namecompany":"Katz","NameJob":"Food Chemist","Address":"195 Lyons Parkway","ImageCompany":"job2.png","Detail":2.0522073575,"DetailCompany":1,"Phone":"508-182-7331","Email":"mhelstrip2h@cyberchimps.com","TimecreatPostDay":"9/4/2020","TimecreatPostHour":"10:05 PM"},
{"linhvuc":"Parttime","loaihinh":"FULLTIME","Namecompany":"Yoveo","NameJob":"Health Coach IV","Address":"2306 Boyd Park","ImageCompany":"VLT.png","Detail":3.5015645661,"DetailCompany":1,"Phone":"330-231-2019","Email":"crhyme2i@wisc.edu","TimecreatPostDay":"9/3/2020","TimecreatPostHour":"1:37 AM"},
{"linhvuc":"Giáo Dục","loaihinh":"Thực tập sinh","Namecompany":"Babblestorm","NameJob":"Computer Systems Analyst II","Address":"049 Springs Plaza","ImageCompany":"job1.jpg","Detail":0.927803364,"DetailCompany":0,"Phone":"102-553-6778","Email":"wlennon2j@paypal.com","TimecreatPostDay":"10/30/2020","TimecreatPostHour":"7:05 AM"},
{"linhvuc":"Kinh Doanh","loaihinh":"FULLTIME","Namecompany":"Buzzshare","NameJob":"Systems Administrator III","Address":"9 Forster Avenue","ImageCompany":"job2.png","Detail":0.1385446231,"DetailCompany":1,"Phone":"822-626-8947","Email":"dcoviello2k@hibu.com","TimecreatPostDay":"5/29/2020","TimecreatPostHour":"5:44 AM"},
{"linhvuc":"Du lịch","loaihinh":"FULLTIME","Namecompany":"Fivechat","NameJob":"VP Accounting","Address":"9 Superior Center","ImageCompany":"VLT.png","Detail":0.6861102225,"DetailCompany":1,"Phone":"173-601-4913","Email":"ejewes2l@jimdo.com","TimecreatPostDay":"11/21/2020","TimecreatPostHour":"7:53 PM"},
{"linhvuc":"Parttime","loaihinh":"PARTTIME","Namecompany":"Myworks","NameJob":"Statistician IV","Address":"7 Cordelia Road","ImageCompany":"job3.jpeg","Detail":3.8166432192,"DetailCompany":0,"Phone":"709-397-1603","Email":"ljollie2m@tiny.cc","TimecreatPostDay":"2/28/2020","TimecreatPostHour":"3:50 PM"},
{"linhvuc":"Bán Hàng","loaihinh":"Thời vụ","Namecompany":"Jazzy","NameJob":"Senior Editor","Address":"27104 Becker Court","ImageCompany":"VLT.jpg","Detail":1.1942867361,"DetailCompany":0,"Phone":"367-299-0777","Email":"ichurching2n@cpanel.net","TimecreatPostDay":"8/1/2020","TimecreatPostHour":"2:14 PM"},
{"linhvuc":"Hành chính","loaihinh":"PARTTIME","Namecompany":"Realbridge","NameJob":"Recruiting Manager","Address":"12 Transport Park","ImageCompany":"job2.png","Detail":0.6204001456,"DetailCompany":0,"Phone":"929-973-1667","Email":"lsherebrook2o@va.gov","TimecreatPostDay":"5/20/2020","TimecreatPostHour":"7:44 AM"},
{"linhvuc":"Tài chính","loaihinh":"PARTTIME","Namecompany":"Mynte","NameJob":"VP Marketing","Address":"923 Graceland Circle","ImageCompany":"VLT.png","Detail":2.4486960275,"DetailCompany":1,"Phone":"701-257-6378","Email":"bwharf2p@edublogs.org","TimecreatPostDay":"12/26/2019","TimecreatPostHour":"1:32 PM"},
{"linhvuc":"Kinh Doanh","loaihinh":"Thời vụ","Namecompany":"Minyx","NameJob":"Community Outreach Specialist","Address":"9 Ramsey Alley","ImageCompany":"VLT.jpg","Detail":0.0551170411,"DetailCompany":0,"Phone":"311-795-6262","Email":"mtommasetti2q@businesswire.com","TimecreatPostDay":"6/2/2020","TimecreatPostHour":"8:19 AM"},
{"linhvuc":"Kế toán","loaihinh":"FULLTIME","Namecompany":"Browsetype","NameJob":"Physical Therapy Assistant","Address":"9716 Corben Crossing","ImageCompany":"job2.png","Detail":0.528785934,"DetailCompany":0,"Phone":"549-575-1411","Email":"fyarham2r@lulu.com","TimecreatPostDay":"10/22/2020","TimecreatPostHour":"3:03 PM"}]